ethz_iam_webservice/__init__.py
ethz_iam_webservice/conn.py
ethz_iam_webservice/group.py
ethz_iam_webservice/guest.py
ethz_iam_webservice/mailinglist.py
ethz_iam_webservice/maillist.py
ethz_iam_webservice/main.py
ethz_iam_webservice/netsupport.py
ethz_iam_webservice/realm.py
ethz_iam_webservice/service.py
ethz_iam_webservice/user.py
ethz_iam_webservice/utils.py
ethz_iam_webservice/verbose.py
ethz_iam_webservice-0.16.10.dist-info/METADATA
ethz_iam_webservice-0.16.10.dist-info/WHEEL
ethz_iam_webservice-0.16.10.dist-info/entry_points.txt
ethz_iam_webservice-0.16.10.dist-info/top_level.txt
ethz_iam_webservice-0.16.10.dist-info/RECORD
