Metadata-Version: 2.4
Name: ethz_iam_webservice
Version: 0.16.10
Summary: Manage users, groups and services of the ETH Identity and Access Management system (IAM)
Author-email: Swen Vermeul <swen@ethz.ch>
License: Apache Software License Version 2.0
Project-URL: Homepage, https://gitlab.ethz.ch/sis/tools/ethz-iam-webservice
Project-URL: Bug Tracker, https://gitlab.ethz.ch/sis/tools/ethz-iam-webservice/-/issues
Classifier: Programming Language :: Python :: 3.9
Classifier: License :: OSI Approved :: Apache Software License
Classifier: Operating System :: OS Independent
Requires-Python: >=3.9
Requires-Dist: requests
Requires-Dist: click>=7.0
Requires-Dist: pyyaml
Requires-Dist: python-dateutil
Requires-Dist: pytz
Provides-Extra: dev
Requires-Dist: pytest; extra == "dev"
